lc_task/__init__.py
lc_task/cli.py
lc_task/py.typed
lc_task/task.py
lc_task-0.3.1.dist-info/LICENSE
lc_task-0.3.1.dist-info/METADATA
lc_task-0.3.1.dist-info/WHEEL
lc_task-0.3.1.dist-info/RECORD
