Metadata-Version: 2.1
Name: lc-task
Version: 0.3.1
Summary: Python library for implementing arbitrary tasks with support for ArgumentParser.
Home-page: https://github.com/libcommon/task-py/
License: MIT
Author: Libcommon
Author-email: 57610970+libcommon@users.noreply.github.com
Requires-Python: >=3.8,<3.12
Classifier: Intended Audience :: Developers
Classifier: License :: OSI Approved :: MIT License
Classifier: Operating System :: OS Independent
Classifier: Programming Language :: Python :: 3
Classifier: Programming Language :: Python :: 3.8
Classifier: Programming Language :: Python :: 3.9
Classifier: Programming Language :: Python :: 3.10
Classifier: Programming Language :: Python :: 3.11
Project-URL: Documentation, https://libcommon.github.io/task-py/
Project-URL: Repository, https://github.com/libcommon/task-py/
